aabbtree.py
aabbtree-2.8.1.dist-info/LICENSE.rst
aabbtree-2.8.1.dist-info/METADATA
aabbtree-2.8.1.dist-info/WHEEL
aabbtree-2.8.1.dist-info/top_level.txt
aabbtree-2.8.1.dist-info/RECORD
