Metadata-Version: 2.1
Name: aabbtree
Version: 2.8.1
Summary: Pure Python implementation of d-dimensional AABB tree.
Home-page: https://github.com/kip-hart/AABBTree
Author: Kenneth (Kip) Hart
Author-email: kiphart91@gmail.com
License: MIT
Project-URL: Documentation, https://aabbtree.readthedocs.io
Keywords: aabb,aabb tree,binary tree
Platform: UNKNOWN
Classifier: Development Status :: 4 - Beta
Classifier: Intended Audience :: Developers
Classifier: Intended Audience :: Science/Research
Classifier: License :: OSI Approved :: MIT License
Classifier: Operating System :: MacOS :: MacOS X
Classifier: Operating System :: Microsoft :: Windows
Classifier: Operating System :: POSIX :: Linux
Classifier: Programming Language :: Python
Classifier: Programming Language :: Python :: 2.7
Classifier: Programming Language :: Python :: 3.4
Classifier: Programming Language :: Python :: 3.5
Classifier: Programming Language :: Python :: 3.6
Classifier: Programming Language :: Python :: 3.7
Classifier: Programming Language :: Python :: 3.8
Classifier: Topic :: Scientific/Engineering
Classifier: Topic :: Scientific/Engineering :: Mathematics
